PygameImagesTools/__init__.py
PygameImagesTools/parallax_bg.py
PygameImagesTools/spritesheet.py
pygameimagestools-0.0.3.dist-info/METADATA
pygameimagestools-0.0.3.dist-info/WHEEL
pygameimagestools-0.0.3.dist-info/licenses/LICENSE
pygameimagestools-0.0.3.dist-info/RECORD
