Metadata-Version: 2.3
Name: PygameImagesTools
Version: 0.0.3
Summary: Library for manage sprite sheet, and pallax background
Project-URL: Homepage, https://github.com/FranckSix/PygameSpriteTools
Project-URL: Issues, https://github.com/FranckSix/PygameSpriteTools/issues
Author-email: FranckSix <francksix@gmail.com>
License-File: LICENSE
Classifier: License :: OSI Approved :: MIT License
Classifier: Operating System :: OS Independent
Classifier: Programming Language :: Python :: 3
Requires-Python: >=3.8
